{
 "cells": [
  {
   "cell_type": "code",
   "execution_count": null,
   "metadata": {},
   "outputs": [
    {
     "name": "stdout",
     "output_type": "stream",
     "text": [
      "The area is:5488.0\n"
     ]
    }
   ],
   "source": [
    "def display(data):\n",
    "    print(f\"The area is:{data}\")\n",
    "\n",
    "def get_input():\n",
    "    length = input(\"Length:\")\n",
    "    width = input(\"Width:\")\n",
    "    return (length, width)\n",
    "\n",
    "def compute_area(length, width):\n",
    "    data = float(length) * float(width)\n",
    "    return data\n",
    "\n",
    "def main():\n",
    "    (length, width) = get_input() #Its a anonymous function\n",
    "    area = compute_area(length, width)\n",
    "    display(area) \n",
    "\n",
    "main()"
   ]
  },
  {
   "cell_type": "code",
   "execution_count": 14,
   "metadata": {},
   "outputs": [
    {
     "name": "stdout",
     "output_type": "stream",
     "text": [
      "Data:This is a message\n",
      "Data:69\n"
     ]
    },
    {
     "data": {
      "text/plain": [
       "'\\nVariables are stored in a stack DS\\nFunction call takes normal time for executing first time\\nFunction call after first take less time to execute due to the machine already knows the location of the varaibles in that function\\n'"
      ]
     },
     "execution_count": 14,
     "metadata": {},
     "output_type": "execute_result"
    }
   ],
   "source": [
    "def display():\n",
    "    x = 10\n",
    "    a = 10\n",
    "    b = 90\n",
    "    c = a + b\n",
    "    print(\"Welcome\")\n",
    "\n",
    "def display(data):\n",
    "    print(f\"Data:{data}\")\n",
    "\n",
    "def main():\n",
    "    display(\"This is a message\")\n",
    "    display(69)\n",
    "    \n",
    "main()\n",
    "\n",
    "'''\n",
    "Variables are stored in a stack DS\n",
    "Function call takes normal time for executing first time\n",
    "Function call after first take less time to execute due to the machine already knows the location of the varaibles in that function\n",
    "'''"
   ]
  },
  {
   "cell_type": "code",
   "execution_count": 24,
   "metadata": {},
   "outputs": [
    {
     "name": "stdout",
     "output_type": "stream",
     "text": [
      "Average of four numbers 10, 20, 30, 40 is: 25.0\n"
     ]
    }
   ],
   "source": [
    "def result_dispaly(ans): #This function is to display the result\n",
    "    print(ans)\n",
    "\n",
    "def take_input():        # This function is for taking input\n",
    "    num1 = int(input(\"Enter number1:\"))\n",
    "    num2 = int(input(\"Enter number2:\"))\n",
    "    num3 = int(input(\"Enter number3:\"))\n",
    "    num4 = int(input(\"Enter number4:\"))\n",
    "    count = int(input(\"Enter the count of numbers: \"))\n",
    "    return (num1, num2, num3, num4, count)\n",
    "\n",
    "def calculate_sum(num1, num2, num3, num4):        # This function is for calculating the sum of four numbers\n",
    "    addition = num1 + num2 + num3 + num4    \n",
    "    return addition\n",
    "\n",
    "def calculate_avg(addition, count): # This function is for calculating the average of four numbers\n",
    "    average = addition / count\n",
    "    return average\n",
    "\n",
    "def main(): # To call all the functions\n",
    "    (num1, num2, num3, num4, count) = take_input()\n",
    "    addition = calculate_sum(num1, num2, num3, num4)\n",
    "    average = calculate_avg(addition, count)\n",
    "    print(f\"Average of four numbers {num1}, {num2}, {num3}, {num4} is: \", end=\"\")\n",
    "    result_dispaly(average)\n",
    "\n",
    "main() "
   ]
  },
  {
   "cell_type": "code",
   "execution_count": 30,
   "metadata": {},
   "outputs": [
    {
     "name": "stdout",
     "output_type": "stream",
     "text": [
      "Biggest number is 9999\n"
     ]
    }
   ],
   "source": [
    "def biggest(ans):\n",
    "    print(f\"Biggest number is {ans}\")\n",
    "\n",
    "def get_input():\n",
    "    num1, num2, num3 = map(int, input().split())\n",
    "    return (num1, num2, num3)\n",
    "\n",
    "def maximum(num1, num2, num3):\n",
    "    if num1 > num2 and num1 > num3:\n",
    "        return (s, num1)\n",
    "    elif num2 > num3:\n",
    "        return num2\n",
    "    else:\n",
    "        return num3\n",
    "def main():\n",
    "    (num1, num2, num3) = get_input()\n",
    "    ans = maximum(num1, num2, num3)\n",
    "    biggest(ans)\n",
    "\n",
    "main()"
   ]
  },
  {
   "cell_type": "code",
   "execution_count": 5,
   "metadata": {},
   "outputs": [
    {
     "name": "stdout",
     "output_type": "stream",
     "text": [
      "Num2 is bigger:3\n",
      "  2           0 RESUME                   0\n",
      "\n",
      "  3           2 LOAD_GLOBAL              1 (NULL + int)\n",
      "             12 LOAD_GLOBAL              3 (NULL + input)\n",
      "             22 CALL                     0\n",
      "             30 CALL                     1\n",
      "             38 STORE_FAST               0 (num1)\n",
      "\n",
      "  4          40 LOAD_FAST                0 (num1)\n",
      "             42 STORE_FAST               1 (ans)\n",
      "\n",
      "  5          44 LOAD_GLOBAL              1 (NULL + int)\n",
      "             54 LOAD_GLOBAL              3 (NULL + input)\n",
      "             64 CALL                     0\n",
      "             72 CALL                     1\n",
      "             80 STORE_FAST               2 (num2)\n",
      "\n",
      "  6          82 LOAD_GLOBAL              1 (NULL + int)\n",
      "             92 LOAD_GLOBAL              3 (NULL + input)\n",
      "            102 CALL                     0\n",
      "            110 CALL                     1\n",
      "            118 STORE_FAST               3 (num3)\n",
      "\n",
      "  7         120 LOAD_FAST                2 (num2)\n",
      "            122 LOAD_FAST                1 (ans)\n",
      "            124 COMPARE_OP              68 (>)\n",
      "            128 POP_JUMP_IF_FALSE       17 (to 164)\n",
      "\n",
      "  8         130 LOAD_FAST                2 (num2)\n",
      "            132 STORE_FAST               1 (ans)\n",
      "\n",
      "  9         134 LOAD_GLOBAL              5 (NULL + print)\n",
      "            144 LOAD_CONST               1 ('Num2 is bigger:')\n",
      "            146 LOAD_FAST                1 (ans)\n",
      "            148 FORMAT_VALUE             0\n",
      "            150 BUILD_STRING             2\n",
      "            152 CALL                     1\n",
      "            160 POP_TOP\n",
      "            162 RETURN_CONST             0 (None)\n",
      "\n",
      " 10     >>  164 LOAD_FAST                3 (num3)\n",
      "            166 LOAD_FAST                1 (ans)\n",
      "            168 COMPARE_OP              68 (>)\n",
      "            172 POP_JUMP_IF_FALSE       17 (to 208)\n",
      "\n",
      " 11         174 LOAD_FAST                3 (num3)\n",
      "            176 STORE_FAST               1 (ans)\n",
      "\n",
      " 12         178 LOAD_GLOBAL              5 (NULL + print)\n",
      "            188 LOAD_CONST               2 ('Num3 is bigger:')\n",
      "            190 LOAD_FAST                1 (ans)\n",
      "            192 FORMAT_VALUE             0\n",
      "            194 BUILD_STRING             2\n",
      "            196 CALL                     1\n",
      "            204 POP_TOP\n",
      "            206 RETURN_CONST             0 (None)\n",
      "\n",
      " 14     >>  208 LOAD_GLOBAL              5 (NULL + print)\n",
      "            218 LOAD_CONST               3 ('Num1 is Bigger:')\n",
      "            220 LOAD_FAST                1 (ans)\n",
      "            222 FORMAT_VALUE             0\n",
      "            224 BUILD_STRING             2\n",
      "            226 CALL                     1\n",
      "            234 POP_TOP\n",
      "            236 RETURN_CONST             0 (None)\n",
      " 16           0 RESUME                   0\n",
      "\n",
      " 17           2 LOAD_GLOBAL              1 (NULL + get_input_compare)\n",
      "             12 CALL                     0\n",
      "             20 POP_TOP\n",
      "\n",
      " 18          22 LOAD_GLOBAL              2 (dis)\n",
      "             32 LOAD_ATTR                3 (NULL|self + dis)\n",
      "             52 LOAD_GLOBAL              0 (get_input_compare)\n",
      "             62 CALL                     1\n",
      "             70 POP_TOP\n",
      "\n",
      " 19          72 LOAD_GLOBAL              2 (dis)\n",
      "             82 LOAD_ATTR                3 (NULL|self + dis)\n",
      "            102 LOAD_GLOBAL              4 (main)\n",
      "            112 CALL                     1\n",
      "            120 POP_TOP\n",
      "            122 RETURN_CONST             0 (None)\n"
     ]
    }
   ],
   "source": [
    "import dis\n",
    "def get_input_compare():\n",
    "    num1 = int(input())\n",
    "    ans = num1\n",
    "    num2 = int(input())\n",
    "    num3 = int(input())\n",
    "    if num2 > ans: \n",
    "        ans = num2\n",
    "        print(f\"Num2 is bigger:{ans}\")\n",
    "    elif num3 > ans:\n",
    "        ans = num3\n",
    "        print(f\"Num3 is bigger:{ans}\")\n",
    "    else:\n",
    "        print(f\"Num1 is Bigger:{ans}\")\n",
    "\n",
    "def main():\n",
    "    get_input_compare()\n",
    "    dis.dis(get_input_compare)\n",
    "    dis.dis(main)\n",
    "main()\n"
   ]
  },
  {
   "cell_type": "code",
   "execution_count": 9,
   "metadata": {},
   "outputs": [
    {
     "name": "stdout",
     "output_type": "stream",
     "text": [
      "Multiplication:6\n",
      "  1           0 RESUME                   0\n",
      "\n",
      "  2           2 LOAD_GLOBAL              1 (NULL + input)\n",
      "             12 CALL                     0\n",
      "             20 STORE_FAST               0 (a)\n",
      "\n",
      "  3          22 LOAD_GLOBAL              1 (NULL + input)\n",
      "             32 CALL                     0\n",
      "             40 STORE_FAST               1 (b)\n",
      "\n",
      "  4          42 LOAD_FAST                0 (a)\n",
      "             44 LOAD_FAST                1 (b)\n",
      "             46 BUILD_TUPLE              2\n",
      "             48 RETURN_VALUE\n",
      "  6           0 RESUME                   0\n",
      "\n",
      "  7           2 LOAD_GLOBAL              1 (NULL + int)\n",
      "             12 LOAD_FAST                0 (a)\n",
      "             14 CALL                     1\n",
      "             22 LOAD_GLOBAL              1 (NULL + int)\n",
      "             32 LOAD_FAST                1 (b)\n",
      "             34 CALL                     1\n",
      "             42 BINARY_OP                5 (*)\n",
      "             46 STORE_FAST               2 (res)\n",
      "\n",
      "  8          48 LOAD_FAST                2 (res)\n",
      "             50 RETURN_VALUE\n",
      " 10           0 RESUME                   0\n",
      "\n",
      " 11           2 LOAD_GLOBAL              1 (NULL + print)\n",
      "             12 LOAD_CONST               1 ('Multiplication:')\n",
      "             14 LOAD_FAST                0 (res)\n",
      "             16 FORMAT_VALUE             0\n",
      "             18 BUILD_STRING             2\n",
      "             20 CALL                     1\n",
      "             28 POP_TOP\n",
      "             30 RETURN_CONST             0 (None)\n",
      " 13           0 RESUME                   0\n",
      "\n",
      " 14           2 LOAD_GLOBAL              1 (NULL + range)\n",
      "             12 LOAD_CONST               1 (1)\n",
      "             14 LOAD_CONST               2 (10)\n",
      "             16 CALL                     2\n",
      "             24 GET_ITER\n",
      "        >>   26 FOR_ITER                 7 (to 44)\n",
      "             30 STORE_FAST               1 (i)\n",
      "\n",
      " 15          32 LOAD_FAST                0 (res)\n",
      "             34 LOAD_FAST                1 (i)\n",
      "             36 BINARY_OP                5 (*)\n",
      "             40 STORE_FAST               0 (res)\n",
      "             42 JUMP_BACKWARD            9 (to 26)\n",
      "\n",
      " 14     >>   44 END_FOR\n",
      "             46 RETURN_CONST             0 (None)\n",
      " 16           0 RESUME                   0\n",
      "\n",
      " 17           2 LOAD_GLOBAL              1 (NULL + take_input)\n",
      "             12 CALL                     0\n",
      "             20 UNPACK_SEQUENCE          2\n",
      "             24 STORE_FAST               0 (a)\n",
      "             26 STORE_FAST               1 (b)\n",
      "\n",
      " 18          28 LOAD_GLOBAL              3 (NULL + multiply)\n",
      "             38 LOAD_FAST                0 (a)\n",
      "             40 LOAD_FAST                1 (b)\n",
      "             42 CALL                     2\n",
      "             50 STORE_FAST               2 (res)\n",
      "\n",
      " 19          52 LOAD_GLOBAL              5 (NULL + display)\n",
      "             62 LOAD_FAST                2 (res)\n",
      "             64 CALL                     1\n",
      "             72 POP_TOP\n",
      "\n",
      " 20          74 LOAD_GLOBAL              7 (NULL + for_loop)\n",
      "             84 LOAD_CONST               1 (9)\n",
      "             86 CALL                     1\n",
      "             94 POP_TOP\n",
      "\n",
      " 21          96 LOAD_GLOBAL              8 (dis)\n",
      "            106 LOAD_ATTR                9 (NULL|self + dis)\n",
      "            126 LOAD_GLOBAL              0 (take_input)\n",
      "            136 CALL                     1\n",
      "            144 POP_TOP\n",
      "\n",
      " 22         146 LOAD_GLOBAL              8 (dis)\n",
      "            156 LOAD_ATTR                9 (NULL|self + dis)\n",
      "            176 LOAD_GLOBAL              2 (multiply)\n",
      "            186 CALL                     1\n",
      "            194 POP_TOP\n",
      "\n",
      " 23         196 LOAD_GLOBAL              8 (dis)\n",
      "            206 LOAD_ATTR                9 (NULL|self + dis)\n",
      "            226 LOAD_GLOBAL              4 (display)\n",
      "            236 CALL                     1\n",
      "            244 POP_TOP\n",
      "\n",
      " 24         246 LOAD_GLOBAL              8 (dis)\n",
      "            256 LOAD_ATTR                9 (NULL|self + dis)\n",
      "            276 LOAD_GLOBAL              6 (for_loop)\n",
      "            286 CALL                     1\n",
      "            294 POP_TOP\n",
      "\n",
      " 25         296 LOAD_GLOBAL              8 (dis)\n",
      "            306 LOAD_ATTR                9 (NULL|self + dis)\n",
      "            326 LOAD_GLOBAL             10 (main)\n",
      "            336 CALL                     1\n",
      "            344 POP_TOP\n",
      "            346 RETURN_CONST             0 (None)\n"
     ]
    }
   ],
   "source": [
    "def take_input():\n",
    "    a = input()\n",
    "    b = input()\n",
    "    return (a, b)\n",
    "\n",
    "def multiply(a, b):\n",
    "    res = int(a) * int(b)\n",
    "    return res\n",
    "\n",
    "def display(res):\n",
    "    print(f\"Multiplication:{res}\")\n",
    "\n",
    "def for_loop(res):\n",
    "    for i in range(1, 10):\n",
    "        res = res * i\n",
    "def main():\n",
    "    (a, b) = take_input()\n",
    "    res = multiply(a, b)\n",
    "    display(res)\n",
    "    for_loop(9)\n",
    "    dis.dis(take_input)\n",
    "    dis.dis(multiply)\n",
    "    dis.dis(display)\n",
    "    dis.dis(for_loop)\n",
    "    dis.dis(main)\n",
    "\n",
    "main()"
   ]
  },
  {
   "cell_type": "code",
   "execution_count": null,
   "metadata": {},
   "outputs": [],
   "source": []
  }
 ],
 "metadata": {
  "language_info": {
   "name": "python"
  }
 },
 "nbformat": 4,
 "nbformat_minor": 2
}
